ml_flow_client/__init__.py
ml_flow_client/main.py
ml_flow_client/skeleton.py
ml_flow_client/flow/__init__.py
ml_flow_client/modell/__init__.py
ml_flow_client/prep/__init__.py
ml_flow_client/prep/prep.py
ml_flow_client/transfer/__init__.py
ml_flow_client/transfer/connector.py
ml_flow_client-0.2.12.dist-info/AUTHORS.rst
ml_flow_client-0.2.12.dist-info/LICENSE.txt
ml_flow_client-0.2.12.dist-info/METADATA
ml_flow_client-0.2.12.dist-info/WHEEL
ml_flow_client-0.2.12.dist-info/top_level.txt
ml_flow_client-0.2.12.dist-info/RECORD
