Metadata-Version: 2.1
Name: ml-flow-client
Version: 0.2.12
Summary: test
Home-page: https://github.com/pyscaffold/pyscaffold/
Author: Sven Haadem
Author-email: svenhaadem@gmail.com
License: mit
Project-URL: Documentation, https://pyscaffold.org/
Platform: any
Classifier: Development Status :: 4 - Beta
Classifier: Programming Language :: Python
Provides-Extra: testing
Requires-Dist: pytest ; extra == 'testing'
Requires-Dist: pytest-cov ; extra == 'testing'
